zscaler/__init__.py
zscaler/zscaler.py
zscaler-0.13.dist-info/LICENSE
zscaler-0.13.dist-info/METADATA
zscaler-0.13.dist-info/WHEEL
zscaler-0.13.dist-info/entry_points.txt
zscaler-0.13.dist-info/top_level.txt
zscaler-0.13.dist-info/RECORD
