Metadata-Version: 2.1
Name: zscaler
Version: 0.13
Summary: A python wrapper for Zscaler API. This project is not affiliated with Zscaler
Home-page: https://github.com/atilavat/Zscaler/
Author: Alok Tilavat
License: UNKNOWN
Keywords: Zscaler API
Platform: UNKNOWN
Requires-Python: >=3, <4
Requires-Dist: requests
